{"id":"benjamin-dehli-rachels-song-cover","releaseId":"","artistName":"Benjamin Dehli","title":"Rachel's Song (Cover)","duration":296000,"durationISO":"PT4M56S","isrcCode":"","genre":"Soundtrack","releaseDate":1728165600000,"spotifyThumbnailUrl":"","thumbnailFilename":"benjaminDehli_rachelsSongCover","links":{"youtube":"https://www.youtube.com/watch?v=JxQQj1ArV9E","youtubeMusic":"https://music.youtube.com/watch?v=JxQQj1ArV9E","soundcloud":"https://soundcloud.com/benjamin-dehli/rachels-song"},"slug":"benjamin-dehli-rachels-song-cover","producedByDehliMusikk":true}