{"id":"0Sape5fh1Yv3OdMtiD4T69","slug":"kaasin-hidden","artistName":"KAASIN","title":"Hidden","duration":240880,"durationISO":"PT4M0S","genre":"Rock","releaseDate":1625184000000,"spotifyThumbnailUrl":"https://i.scdn.co/image/ab67616d0000b273e99b4ae0bc64ea747b8150c4","thumbnailFilename":"kAASIN_hidden","links":{"youtube":"https://www.youtube.com/watch?v=JVMVHggx-0w","youtubeMusic":"https://music.youtube.com/watch?v=JVMVHggx-0w","soundcloud":"https://soundcloud.com/benjamin-dehli/kaasin-hidden-2025-remix"},"composedByDehliMusikk":true,"producedByDehliMusikk":true,"isrcCode":"DEUJ62100257"}