{"id":"67zA6BMkPFEtl2i1dQiJKN","releaseId":"","artistName":"KAASIN","title":"Dead Man's Hand","duration":240100,"durationISO":"PT4M0S","isrcCode":"NOEGB2409010","genre":"Rock","releaseDate":1732233600000,"spotifyThumbnailUrl":"https://i.scdn.co/image/ab67616d0000b2733929962d47581885a7adcf20","thumbnailFilename":"kAASIN_deadMansHand","links":{"spotify":"https://open.spotify.com/track/67zA6BMkPFEtl2i1dQiJKN","deezer":"https://www.deezer.com/track/3090267921","pandora":"https://www.pandora.com/TR:141792708","tidal":"https://listen.tidal.com/track/399344118","yandex":"https://music.yandex.ru/track/132924318"},"slug":"kaasin-dead-mans-hand"}