[{
    "id": "2020031401",
    "timestamp": 1584144000000,
    "title": {
      "no": "Innspilling av Korg MS-20 arpeggioer",
      "en": "Recording Korg MS-20 arpeggios"
    },
    "content": {
      "no": "Innspilling av arpeggioer med en Korg MS-20 synth, analog ekko og fjærklang\nNotene kommer som MIDI signal fra Logic og gjort om til styrespenning med en Korg SQ-1",
      "en": "Recording some arpeggios with the Korg MS-20 synthesizer, analog delay and spring reverb\nThe notes are coming from Logic as MIDI signal and converted into control voltage with a Korg SQ-1"
    },
    "thumbnailDescription": "Korg MS-20 synthesizer",
    "thumbnailFilename": "2020-03-14-01",
    "link": {
      "url": "https://youtu.be/ZsHg94LOXHw",
      "text": {
        "en": "Show video",
        "no": "Se video"
      }
    }
  },
  {
    "id": "2020031400",
    "timestamp": 1584144000000,
    "title": {
      "no": "Clavinet med wah-pedal",
      "en": "Clavinet with wah-pedal"
    },
    "content": {
      "no": "Innspilling av Clavinet D6 med Real McCoy Custom Picture Wah og ProCo Rat vreng",
      "en": "Recording Clavinet D6 with Real McCoy Custom Picture Wah and ProCo Rat distortion"
    },
    "thumbnailDescription": "Effects pedals",
    "thumbnailFilename": "2020-03-14-00",
    "link": {
      "url": "https://www.instagram.com/p/B9tVPHUFD4f/",
      "text": {
        "en": "Show video",
        "no": "Se video"
      }
    }
  },
  {
    "id": "2020030801",
    "timestamp": 1583625600000,
    "title": {
      "no": "Tangentpålegg",
      "en": "Layering keyboard tracks"
    },
    "content": {
      "no": "Pålegg av forskjellige tangentinstrumenter i Logic 🎹🎹🎹",
      "en": "Layering different keyboard instruments in Logic 🎹🎹🎹"
    },
    "thumbnailDescription": "Computer screen with Logic session",
    "thumbnailFilename": "2020-03-08-01",
    "link": {
      "url": "https://www.instagram.com/p/B9fKf_hFYgs/",
      "text": {
        "en": "Show video",
        "no": "Se video"
      }
    }
  }
]
